[{"Continent ID":"af","Continent":"Africa","Country ID":"afciv","Country":"Cote d'Ivoire","ISO 3":"civ","Trade Value":8287},{"Continent ID":"af","Continent":"Africa","Country ID":"afcmr","Country":"Cameroon","ISO 3":"cmr","Trade Value":3211},{"Continent ID":"af","Continent":"Africa","Country ID":"afdza","Country":"Algeria","ISO 3":"dza","Trade Value":26060},{"Continent ID":"af","Continent":"Africa","Country ID":"afegy","Country":"Egypt","ISO 3":"egy","Trade Value":12540},{"Continent ID":"af","Continent":"Africa","Country ID":"afeth","Country":"Ethiopia","ISO 3":"eth","Trade Value":41581},{"Continent ID":"af","Continent":"Africa","Country ID":"afgin","Country":"Guinea","ISO 3":"gin","Trade Value":21733},{"Continent ID":"af","Continent":"Africa","Country ID":"afken","Country":"Kenya","ISO 3":"ken","Trade Value":11439},{"Continent ID":"af","Continent":"Africa","Country ID":"aflby","Country":"Libya","ISO 3":"lby","Trade Value":93843},{"Continent ID":"af","Continent":"Africa","Country ID":"afmar","Country":"Morocco","ISO 3":"mar","Trade Value":657765},{"Continent ID":"af","Continent":"Africa","Country ID":"afmdg","Country":"Madagascar","ISO 3":"mdg","Trade Value":1141},{"Continent ID":"af","Continent":"Africa","Country ID":"afmli","Country":"Mali","ISO 3":"mli","Trade Value":1033},{"Continent ID":"af","Continent":"Africa","Country ID":"afmus","Country":"Mauritius","ISO 3":"mus","Trade Value":11083},{"Continent ID":"af","Continent":"Africa","Country ID":"afmyt","Country":"Mayotte","ISO 3":"myt","Trade Value":11322},{"Continent ID":"af","Continent":"Africa","Country ID":"afnam","Country":"Namibia","ISO 3":"nam","Trade Value":1954},{"Continent ID":"af","Continent":"Africa","Country ID":"afner","Country":"Niger","ISO 3":"ner","Trade Value":9449},{"Continent ID":"af","Continent":"Africa","Country ID":"afsdn","Country":"Sudan","ISO 3":"sdn","Trade Value":243},{"Continent ID":"af","Continent":"Africa","Country ID":"afsen","Country":"Senegal","ISO 3":"sen","Trade Value":472.00000000000006},{"Continent ID":"af","Continent":"Africa","Country ID":"afswz","Country":"Eswatini","ISO 3":"swz","Trade Value":231338},{"Continent ID":"af","Continent":"Africa","Country ID":"aftun","Country":"Tunisia","ISO 3":"tun","Trade Value":364232},{"Continent ID":"af","Continent":"Africa","Country ID":"afzaf","Country":"South Africa","ISO 3":"zaf","Trade Value":4241407},{"Continent ID":"af","Continent":"Africa","Country ID":"afzmb","Country":"Zambia","ISO 3":"zmb","Trade Value":2173},{"Continent ID":"as","Continent":"Asia","Country ID":"asare","Country":"United Arab Emirates","ISO 3":"are","Trade Value":2366026},{"Continent ID":"as","Continent":"Asia","Country ID":"asarm","Country":"Armenia","ISO 3":"arm","Trade Value":54537},{"Continent ID":"as","Continent":"Asia","Country ID":"asaze","Country":"Azerbaijan","ISO 3":"aze","Trade Value":436},{"Continent ID":"as","Continent":"Asia","Country ID":"asbhr","Country":"Bahrain","ISO 3":"bhr","Trade Value":193914},{"Continent ID":"as","Continent":"Asia","Country ID":"asbrn","Country":"Brunei","ISO 3":"brn","Trade Value":22373},{"Continent ID":"as","Continent":"Asia","Country ID":"asbtn","Country":"Bhutan","ISO 3":"btn","Trade Value":315403},{"Continent ID":"as","Continent":"Asia","Country ID":"aschn","Country":"China","ISO 3":"chn","Trade Value":7540558},{"Continent ID":"as","Continent":"Asia","Country ID":"ascyp","Country":"Cyprus","ISO 3":"cyp","Trade Value":631203},{"Continent ID":"as","Continent":"Asia","Country ID":"asgeo","Country":"Georgia","ISO 3":"geo","Trade Value":25843},{"Continent ID":"as","Continent":"Asia","Country ID":"ashkg","Country":"Hong Kong","ISO 3":"hkg","Trade Value":8990116},{"Continent ID":"as","Continent":"Asia","Country ID":"asidn","Country":"Indonesia","ISO 3":"idn","Trade Value":327068},{"Continent ID":"as","Continent":"Asia","Country ID":"asind","Country":"India","ISO 3":"ind","Trade Value":1806878},{"Continent ID":"as","Continent":"Asia","Country ID":"asirn","Country":"Iran","ISO 3":"irn","Trade Value":178822.99999999997},{"Continent ID":"as","Continent":"Asia","Country ID":"asjor","Country":"Jordan","ISO 3":"jor","Trade Value":249256},{"Continent ID":"as","Continent":"Asia","Country ID":"asjpn","Country":"Japan","ISO 3":"jpn","Trade Value":22696650},{"Continent ID":"as","Continent":"Asia","Country ID":"askaz","Country":"Kazakhstan","ISO 3":"kaz","Trade Value":244666},{"Continent ID":"as","Continent":"Asia","Country ID":"askor","Country":"South Korea","ISO 3":"kor","Trade Value":4622713},{"Continent ID":"as","Continent":"Asia","Country ID":"askwt","Country":"Kuwait","ISO 3":"kwt","Trade Value":3999487},{"Continent ID":"as","Continent":"Asia","Country ID":"aslao","Country":"Laos","ISO 3":"lao","Trade Value":45704},{"Continent ID":"as","Continent":"Asia","Country ID":"aslbn","Country":"Lebanon","ISO 3":"lbn","Trade Value":1470812},{"Continent ID":"as","Continent":"Asia","Country ID":"aslka","Country":"Sri Lanka","ISO 3":"lka","Trade Value":9381},{"Continent ID":"as","Continent":"Asia","Country ID":"asmac","Country":"Macau","ISO 3":"mac","Trade Value":3260},{"Continent ID":"as","Continent":"Asia","Country ID":"asmng","Country":"Mongolia","ISO 3":"mng","Trade Value":134764},{"Continent ID":"as","Continent":"Asia","Country ID":"asmys","Country":"Malaysia","ISO 3":"mys","Trade Value":1424591},{"Continent ID":"as","Continent":"Asia","Country ID":"asnpl","Country":"Nepal","ISO 3":"npl","Trade Value":154733},{"Continent ID":"as","Continent":"Asia","Country ID":"asomn","Country":"Oman","ISO 3":"omn","Trade Value":225725},{"Continent ID":"as","Continent":"Asia","Country ID":"aspak","Country":"Pakistan","ISO 3":"pak","Trade Value":461597},{"Continent ID":"as","Continent":"Asia","Country ID":"asphl","Country":"Philippines","ISO 3":"phl","Trade Value":105217},{"Continent ID":"as","Continent":"Asia","Country ID":"asprk","Country":"North Korea","ISO 3":"prk","Trade Value":24043.000000000004},{"Continent ID":"as","Continent":"Asia","Country ID":"asqat","Country":"Qatar","ISO 3":"qat","Trade Value":2150579},{"Continent ID":"as","Continent":"Asia","Country ID":"assau","Country":"Saudi Arabia","ISO 3":"sau","Trade Value":6188495},{"Continent ID":"as","Continent":"Asia","Country ID":"assgp","Country":"Singapore","ISO 3":"sgp","Trade Value":30942475},{"Continent ID":"as","Continent":"Asia","Country ID":"astha","Country":"Thailand","ISO 3":"tha","Trade Value":142357},{"Continent ID":"as","Continent":"Asia","Country ID":"astur","Country":"Turkey","ISO 3":"tur","Trade Value":38922071},{"Continent ID":"as","Continent":"Asia","Country ID":"asvnm","Country":"Vietnam","ISO 3":"vnm","Trade Value":46193},{"Continent ID":"as","Continent":"Asia","Country ID":"asxxb","Country":"Chinese Taipei","ISO 3":null,"Trade Value":2866650},{"Continent ID":"as","Continent":"Asia","Country ID":"asyem","Country":"Yemen","ISO 3":"yem","Trade Value":534},{"Continent ID":"eu","Continent":"Europe","Country ID":"eualb","Country":"Albania","ISO 3":"alb","Trade Value":32914},{"Continent ID":"eu","Continent":"Europe","Country ID":"euand","Country":"Andorra","ISO 3":"and","Trade Value":338767},{"Continent ID":"eu","Continent":"Europe","Country ID":"euaut","Country":"Austria","ISO 3":"aut","Trade Value":79393010},{"Continent ID":"eu","Continent":"Europe","Country ID":"eubel","Country":"Belgium","ISO 3":"bel","Trade Value":152324924},{"Continent ID":"eu","Continent":"Europe","Country ID":"eubgr","Country":"Bulgaria","ISO 3":"bgr","Trade Value":505672},{"Continent ID":"eu","Continent":"Europe","Country ID":"eubih","Country":"Bosnia and Herzegovina","ISO 3":"bih","Trade Value":488875},{"Continent ID":"eu","Continent":"Europe","Country ID":"eublr","Country":"Belarus","ISO 3":"blr","Trade Value":84702},{"Continent ID":"eu","Continent":"Europe","Country ID":"euche","Country":"Switzerland","ISO 3":"che","Trade Value":36738494},{"Continent ID":"eu","Continent":"Europe","Country ID":"eucze","Country":"Czechia","ISO 3":"cze","Trade Value":18212326},{"Continent ID":"eu","Continent":"Europe","Country ID":"eudeu","Country":"Germany","ISO 3":"deu","Trade Value":751924014},{"Continent ID":"eu","Continent":"Europe","Country ID":"eudnk","Country":"Denmark","ISO 3":"dnk","Trade Value":30939357},{"Continent ID":"eu","Continent":"Europe","Country ID":"euesp","Country":"Spain","ISO 3":"esp","Trade Value":173370432},{"Continent ID":"eu","Continent":"Europe","Country ID":"euest","Country":"Estonia","ISO 3":"est","Trade Value":1511627},{"Continent ID":"eu","Continent":"Europe","Country ID":"eufin","Country":"Finland","ISO 3":"fin","Trade Value":20073984},{"Continent ID":"eu","Continent":"Europe","Country ID":"eufra","Country":"France","ISO 3":"fra","Trade Value":295658863},{"Continent ID":"eu","Continent":"Europe","Country ID":"eugbr","Country":"United Kingdom","ISO 3":"gbr","Trade Value":623221532},{"Continent ID":"eu","Continent":"Europe","Country ID":"eugrc","Country":"Greece","ISO 3":"grc","Trade Value":9359949},{"Continent ID":"eu","Continent":"Europe","Country ID":"euhrv","Country":"Croatia","ISO 3":"hrv","Trade Value":4301650},{"Continent ID":"eu","Continent":"Europe","Country ID":"euhun","Country":"Hungary","ISO 3":"hun","Trade Value":3599178},{"Continent ID":"eu","Continent":"Europe","Country ID":"euirl","Country":"Ireland","ISO 3":"irl","Trade Value":56121886},{"Continent ID":"eu","Continent":"Europe","Country ID":"euisl","Country":"Iceland","ISO 3":"isl","Trade Value":1385007},{"Continent ID":"eu","Continent":"Europe","Country ID":"euita","Country":"Italy","ISO 3":"ita","Trade Value":140823475},{"Continent ID":"eu","Continent":"Europe","Country ID":"eultu","Country":"Lithuania","ISO 3":"ltu","Trade Value":131138.00000000003},{"Continent ID":"eu","Continent":"Europe","Country ID":"eulva","Country":"Latvia","ISO 3":"lva","Trade Value":217280},{"Continent ID":"eu","Continent":"Europe","Country ID":"eumda","Country":"Moldova","ISO 3":"mda","Trade Value":73111},{"Continent ID":"eu","Continent":"Europe","Country ID":"eumkd","Country":"North Macedonia","ISO 3":"mkd","Trade Value":158320},{"Continent ID":"eu","Continent":"Europe","Country ID":"eumlt","Country":"Malta","ISO 3":"mlt","Trade Value":344195},{"Continent ID":"eu","Continent":"Europe","Country ID":"eumne","Country":"Montenegro","ISO 3":"mne","Trade Value":171916},{"Continent ID":"eu","Continent":"Europe","Country ID":"eunld","Country":"Netherlands","ISO 3":"nld","Trade Value":132582098},{"Continent ID":"eu","Continent":"Europe","Country ID":"eunor","Country":"Norway","ISO 3":"nor","Trade Value":22674182},{"Continent ID":"eu","Continent":"Europe","Country ID":"eupol","Country":"Poland","ISO 3":"pol","Trade Value":19721603},{"Continent ID":"eu","Continent":"Europe","Country ID":"euprt","Country":"Portugal","ISO 3":"prt","Trade Value":3514205},{"Continent ID":"eu","Continent":"Europe","Country ID":"eurou","Country":"Romania","ISO 3":"rou","Trade Value":1962360},{"Continent ID":"eu","Continent":"Europe","Country ID":"eurus","Country":"Russia","ISO 3":"rus","Trade Value":9134723},{"Continent ID":"eu","Continent":"Europe","Country ID":"eusrb","Country":"Serbia","ISO 3":"srb","Trade Value":1769060},{"Continent ID":"eu","Continent":"Europe","Country ID":"eusvk","Country":"Slovakia","ISO 3":"svk","Trade Value":7319308},{"Continent ID":"eu","Continent":"Europe","Country ID":"eusvn","Country":"Slovenia","ISO 3":"svn","Trade Value":6015850},{"Continent ID":"eu","Continent":"Europe","Country ID":"euswe","Country":"Sweden","ISO 3":"swe","Trade Value":58073672},{"Continent ID":"eu","Continent":"Europe","Country ID":"euukr","Country":"Ukraine","ISO 3":"ukr","Trade Value":513920},{"Continent ID":"na","Continent":"North America","Country ID":"naant","Country":"Netherlands Antilles","ISO 3":"ant","Trade Value":1980},{"Continent ID":"na","Continent":"North America","Country ID":"nabrb","Country":"Barbados","ISO 3":"brb","Trade Value":30843},{"Continent ID":"na","Continent":"North America","Country ID":"nacan","Country":"Canada","ISO 3":"can","Trade Value":214494338},{"Continent ID":"na","Continent":"North America","Country ID":"nacri","Country":"Costa Rica","ISO 3":"cri","Trade Value":203316},{"Continent ID":"na","Continent":"North America","Country ID":"nacub","Country":"Cuba","ISO 3":"cub","Trade Value":1022},{"Continent ID":"na","Continent":"North America","Country ID":"nadma","Country":"Dominica","ISO 3":"dma","Trade Value":731.0000000000001},{"Continent ID":"na","Continent":"North America","Country ID":"nagrl","Country":"Greenland","ISO 3":"grl","Trade Value":41176},{"Continent ID":"na","Continent":"North America","Country ID":"nagtm","Country":"Guatemala","ISO 3":"gtm","Trade Value":2555},{"Continent ID":"na","Continent":"North America","Country ID":"najam","Country":"Jamaica","ISO 3":"jam","Trade Value":6610},{"Continent ID":"na","Continent":"North America","Country ID":"namex","Country":"Mexico","ISO 3":"mex","Trade Value":27833724},{"Continent ID":"na","Continent":"North America","Country ID":"nanic","Country":"Nicaragua","ISO 3":"nic","Trade Value":89521},{"Continent ID":"na","Continent":"North America","Country ID":"napan","Country":"Panama","ISO 3":"pan","Trade Value":956010},{"Continent ID":"na","Continent":"North America","Country ID":"naslv","Country":"El Salvador","ISO 3":"slv","Trade Value":288301},{"Continent ID":"na","Continent":"North America","Country ID":"natto","Country":"Trinidad and Tobago","ISO 3":"tto","Trade Value":13595},{"Continent ID":"na","Continent":"North America","Country ID":"nausa","Country":"United States","ISO 3":"usa","Trade Value":2252633778},{"Continent ID":"oc","Continent":"Oceania","Country ID":"ocaus","Country":"Australia","ISO 3":"aus","Trade Value":4667717},{"Continent ID":"oc","Continent":"Oceania","Country ID":"ocgum","Country":"Guam","ISO 3":"gum","Trade Value":8891},{"Continent ID":"oc","Continent":"Oceania","Country ID":"ocncl","Country":"New Caledonia","ISO 3":"ncl","Trade Value":470025},{"Continent ID":"oc","Continent":"Oceania","Country ID":"ocnzl","Country":"New Zealand","ISO 3":"nzl","Trade Value":527686},{"Continent ID":"oc","Continent":"Oceania","Country ID":"ocpng","Country":"Papua New Guinea","ISO 3":"png","Trade Value":25877},{"Continent ID":"oc","Continent":"Oceania","Country ID":"ocpyf","Country":"French Polynesia","ISO 3":"pyf","Trade Value":65056},{"Continent ID":"oc","Continent":"Oceania","Country ID":"ocwlf","Country":"Wallis and Futuna","ISO 3":"wlf","Trade Value":2146},{"Continent ID":"sa","Continent":"South America","Country ID":"saarg","Country":"Argentina","ISO 3":"arg","Trade Value":2013640},{"Continent ID":"sa","Continent":"South America","Country ID":"sabol","Country":"Bolivia","ISO 3":"bol","Trade Value":22285},{"Continent ID":"sa","Continent":"South America","Country ID":"sabra","Country":"Brazil","ISO 3":"bra","Trade Value":4892723},{"Continent ID":"sa","Continent":"South America","Country ID":"sachl","Country":"Chile","ISO 3":"chl","Trade Value":1314090},{"Continent ID":"sa","Continent":"South America","Country ID":"sacol","Country":"Colombia","ISO 3":"col","Trade Value":494013},{"Continent ID":"sa","Continent":"South America","Country ID":"saecu","Country":"Ecuador","ISO 3":"ecu","Trade Value":117593},{"Continent ID":"sa","Continent":"South America","Country ID":"saper","Country":"Peru","ISO 3":"per","Trade Value":883751},{"Continent ID":"sa","Continent":"South America","Country ID":"sapry","Country":"Paraguay","ISO 3":"pry","Trade Value":28106},{"Continent ID":"sa","Continent":"South America","Country ID":"saury","Country":"Uruguay","ISO 3":"ury","Trade Value":349254},{"Continent ID":"sa","Continent":"South America","Country ID":"saven","Country":"Venezuela","ISO 3":"ven","Trade Value":163026}]