[{"Section ID":1,"Section":"Animal Products","HS2 ID":101,"HS2":"Live animals","Trade Value":713644.0000000001},{"Section ID":1,"Section":"Animal Products","HS2 ID":102,"HS2":"Meat & edible offal","Trade Value":282408},{"Section ID":1,"Section":"Animal Products","HS2 ID":103,"HS2":"Fish, crustaceans, & molluscs","Trade Value":356306970},{"Section ID":1,"Section":"Animal Products","HS2 ID":104,"HS2":"Edible products of animal origin, n.e.s.","Trade Value":76667},{"Section ID":1,"Section":"Animal Products","HS2 ID":105,"HS2":"Animal originated products, n.e.s.","Trade Value":1100337},{"Section ID":2,"Section":"Vegetable Products","HS2 ID":206,"HS2":"Live trees, plants, bulbs, cut flowers, & ornamental foliage","Trade Value":432204},{"Section ID":2,"Section":"Vegetable Products","HS2 ID":207,"HS2":"Edible vegetables, roots, & tubers","Trade Value":22168011},{"Section ID":2,"Section":"Vegetable Products","HS2 ID":208,"HS2":"Edible fruits, nuts & fruit peels","Trade Value":2511294},{"Section ID":2,"Section":"Vegetable Products","HS2 ID":209,"HS2":"Coffee, tea, mate & spices","Trade Value":18599534},{"Section ID":2,"Section":"Vegetable Products","HS2 ID":210,"HS2":"Cereals","Trade Value":875439},{"Section ID":2,"Section":"Vegetable Products","HS2 ID":211,"HS2":"Products of the milling industry","Trade Value":43432},{"Section ID":2,"Section":"Vegetable Products","HS2 ID":212,"HS2":"Oils seeds, oleaginous fruits, grains, straw & fodder","Trade Value":65416},{"Section ID":2,"Section":"Vegetable Products","HS2 ID":213,"HS2":"Natural gums, resins & other vegetable extracts","Trade Value":23250},{"Section ID":2,"Section":"Vegetable Products","HS2 ID":214,"HS2":"Vegetable plaiting materials & products, n.e.s.","Trade Value":949302},{"Section ID":3,"Section":"Animal and Vegetable Bi-Products","HS2 ID":315,"HS2":"Animal or vegetable fats, oils, & waxes","Trade Value":205285},{"Section ID":4,"Section":"Foodstuffs","HS2 ID":416,"HS2":"Preparations of fish, crustacenas, & molluscs","Trade Value":9731279},{"Section ID":4,"Section":"Foodstuffs","HS2 ID":417,"HS2":"Sugars & confectioneries","Trade Value":81920},{"Section ID":4,"Section":"Foodstuffs","HS2 ID":418,"HS2":"Cocoa & cocoa preparations","Trade Value":2732},{"Section ID":4,"Section":"Foodstuffs","HS2 ID":419,"HS2":"Preparations of cereals, flour, starch or milk","Trade Value":1243592},{"Section ID":4,"Section":"Foodstuffs","HS2 ID":420,"HS2":"Preparations of vegetables, fruit, nuts or other plant parts","Trade Value":400705},{"Section ID":4,"Section":"Foodstuffs","HS2 ID":421,"HS2":"Miscellaneous edible preparations","Trade Value":1286917},{"Section ID":4,"Section":"Foodstuffs","HS2 ID":422,"HS2":"Beverages, spirits, & vinegar","Trade Value":153267},{"Section ID":4,"Section":"Foodstuffs","HS2 ID":423,"HS2":"Food residues & wastes; animal fodder","Trade Value":50595},{"Section ID":4,"Section":"Foodstuffs","HS2 ID":424,"HS2":"Tobacco & substitutes","Trade Value":5553192},{"Section ID":5,"Section":"Mineral Products","HS2 ID":525,"HS2":"Salt, sulphur, cement, lime, stone, & plaster","Trade Value":44878},{"Section ID":5,"Section":"Mineral Products","HS2 ID":527,"HS2":"Mineral fuels, mineral oils and products of their distillation","Trade Value":17860697},{"Section ID":6,"Section":"Chemical Products","HS2 ID":628,"HS2":"Inorganic chemicals","Trade Value":13149358},{"Section ID":6,"Section":"Chemical Products","HS2 ID":629,"HS2":"Organic chemicals","Trade Value":172117},{"Section ID":6,"Section":"Chemical Products","HS2 ID":630,"HS2":"Pharmaceutical products","Trade Value":10370153},{"Section ID":6,"Section":"Chemical Products","HS2 ID":631,"HS2":"Fertilizers","Trade Value":34793205},{"Section ID":6,"Section":"Chemical Products","HS2 ID":632,"HS2":"Paints, dyes, & varnishes","Trade Value":611776},{"Section ID":6,"Section":"Chemical Products","HS2 ID":633,"HS2":"Perfumery & cosmetics","Trade Value":571207},{"Section ID":6,"Section":"Chemical Products","HS2 ID":634,"HS2":"Soap, cleaners, candles, dental, modelling pastes","Trade Value":299765},{"Section ID":6,"Section":"Chemical Products","HS2 ID":635,"HS2":"Glues, starches, & albuminoid products","Trade Value":356383},{"Section ID":6,"Section":"Chemical Products","HS2 ID":637,"HS2":"Photo & movie goods","Trade Value":156275},{"Section ID":6,"Section":"Chemical Products","HS2 ID":638,"HS2":"Chemical products n.e.s.","Trade Value":290553},{"Section ID":7,"Section":"Plastics and Rubbers","HS2 ID":739,"HS2":"Plastics & articles thereof","Trade Value":19054439},{"Section ID":7,"Section":"Plastics and Rubbers","HS2 ID":740,"HS2":"Rubber & articles thereof","Trade Value":495461},{"Section ID":8,"Section":"Animal Hides","HS2 ID":841,"HS2":"Raw hides & skin (non-fur)","Trade Value":225197567},{"Section ID":8,"Section":"Animal Hides","HS2 ID":842,"HS2":"Leather articles","Trade Value":24456704},{"Section ID":8,"Section":"Animal Hides","HS2 ID":843,"HS2":"Furskins, articifial fur, & articles","Trade Value":1907},{"Section ID":9,"Section":"Wood Products","HS2 ID":944,"HS2":"Wood, wood articles, & charcoal","Trade Value":4719572},{"Section ID":9,"Section":"Wood Products","HS2 ID":945,"HS2":"Cork & cork articles","Trade Value":99},{"Section ID":9,"Section":"Wood Products","HS2 ID":946,"HS2":"Straw & esparto manufactures","Trade Value":3993837},{"Section ID":10,"Section":"Paper Goods","HS2 ID":1047,"HS2":"Wood pulp & paper scrap","Trade Value":21316},{"Section ID":10,"Section":"Paper Goods","HS2 ID":1048,"HS2":"Paper articles","Trade Value":1351480},{"Section ID":10,"Section":"Paper Goods","HS2 ID":1049,"HS2":"Books, newspapers, & other prints","Trade Value":11073253},{"Section ID":11,"Section":"Textiles","HS2 ID":1150,"HS2":"Silk","Trade Value":374619},{"Section ID":11,"Section":"Textiles","HS2 ID":1151,"HS2":"Wool & animal hair","Trade Value":257863},{"Section ID":11,"Section":"Textiles","HS2 ID":1152,"HS2":"Cotton","Trade Value":21421117},{"Section ID":11,"Section":"Textiles","HS2 ID":1153,"HS2":"Vegetable textile fibers, paper yarn & fabrics","Trade Value":286355645},{"Section ID":11,"Section":"Textiles","HS2 ID":1154,"HS2":"Man-made filaments","Trade Value":3016016},{"Section ID":11,"Section":"Textiles","HS2 ID":1155,"HS2":"Man-made staple fibres","Trade Value":5001357},{"Section ID":11,"Section":"Textiles","HS2 ID":1156,"HS2":"Wadding, felt, nonwovens, twin, ropes, & articles thereof","Trade Value":20398461},{"Section ID":11,"Section":"Textiles","HS2 ID":1157,"HS2":"Carpets & textile floor covers","Trade Value":1645204},{"Section ID":11,"Section":"Textiles","HS2 ID":1158,"HS2":"Special woven fabrics and tapestries","Trade Value":20438917},{"Section ID":11,"Section":"Textiles","HS2 ID":1159,"HS2":"Coated, covered, & laminated fabrics for industrial use","Trade Value":650394},{"Section ID":11,"Section":"Textiles","HS2 ID":1160,"HS2":"Knitted fabrics","Trade Value":1090249},{"Section ID":11,"Section":"Textiles","HS2 ID":1161,"HS2":"Knitted clothing accesories","Trade Value":2359346008},{"Section ID":11,"Section":"Textiles","HS2 ID":1162,"HS2":"Non-knitted clothing accesories","Trade Value":3022623138},{"Section ID":11,"Section":"Textiles","HS2 ID":1163,"HS2":"Used clothes & textile articles","Trade Value":398649696},{"Section ID":12,"Section":"Footwear and Headwear","HS2 ID":1264,"HS2":"Footwear","Trade Value":70832278},{"Section ID":12,"Section":"Footwear and Headwear","HS2 ID":1265,"HS2":"Headgear","Trade Value":153354113},{"Section ID":12,"Section":"Footwear and Headwear","HS2 ID":1266,"HS2":"Umbrellas, walking sticks, & whips","Trade Value":166508},{"Section ID":12,"Section":"Footwear and Headwear","HS2 ID":1267,"HS2":"Feather articles, feathers, artificial flowers, & articles of human hair","Trade Value":304256},{"Section ID":13,"Section":"Stone And Glass","HS2 ID":1368,"HS2":"Stone, plaster, cement, asbestos, mica.","Trade Value":195107},{"Section ID":13,"Section":"Stone And Glass","HS2 ID":1369,"HS2":"Ceramic products","Trade Value":25687674},{"Section ID":13,"Section":"Stone And Glass","HS2 ID":1370,"HS2":"Glass & glassware","Trade Value":2451532},{"Section ID":14,"Section":"Precious Metals","HS2 ID":1471,"HS2":"Precious stones, metals, & pearls","Trade Value":370042},{"Section ID":15,"Section":"Metals","HS2 ID":1572,"HS2":"Iron & steel","Trade Value":2059851.9999999998},{"Section ID":15,"Section":"Metals","HS2 ID":1573,"HS2":"Iron or steel articles","Trade Value":4035700},{"Section ID":15,"Section":"Metals","HS2 ID":1574,"HS2":"Copper articles","Trade Value":3534736},{"Section ID":15,"Section":"Metals","HS2 ID":1575,"HS2":"Nickel articles","Trade Value":6710},{"Section ID":15,"Section":"Metals","HS2 ID":1576,"HS2":"Aluminum articles","Trade Value":410959},{"Section ID":15,"Section":"Metals","HS2 ID":1578,"HS2":"Lead articles","Trade Value":125758},{"Section ID":15,"Section":"Metals","HS2 ID":1579,"HS2":"Zinc articles","Trade Value":61839},{"Section ID":15,"Section":"Metals","HS2 ID":1580,"HS2":"Tin articles","Trade Value":45762},{"Section ID":15,"Section":"Metals","HS2 ID":1581,"HS2":"Cermet articles","Trade Value":705},{"Section ID":15,"Section":"Metals","HS2 ID":1582,"HS2":"Tools & cutlery","Trade Value":929053},{"Section ID":15,"Section":"Metals","HS2 ID":1583,"HS2":"Miscellaneous metal products","Trade Value":329652},{"Section ID":16,"Section":"Machines","HS2 ID":1684,"HS2":"Machinery, mechanical appliances, & parts","Trade Value":43997584},{"Section ID":16,"Section":"Machines","HS2 ID":1685,"HS2":"Electrical machinery and electronics","Trade Value":21212792},{"Section ID":17,"Section":"Transportation","HS2 ID":1786,"HS2":"Railway and trams","Trade Value":275844},{"Section ID":17,"Section":"Transportation","HS2 ID":1787,"HS2":"Cars, tractors, trucks & parts thereof.","Trade Value":17852262},{"Section ID":17,"Section":"Transportation","HS2 ID":1788,"HS2":"Aircraft and spacecraft","Trade Value":817765},{"Section ID":17,"Section":"Transportation","HS2 ID":1789,"HS2":"Ships, boats, & floating structures","Trade Value":2442016},{"Section ID":18,"Section":"Instruments","HS2 ID":1890,"HS2":"Optical, photo, & film equipment; medical instruments","Trade Value":18698244},{"Section ID":18,"Section":"Instruments","HS2 ID":1891,"HS2":"Clocks, watches, & parts","Trade Value":99842},{"Section ID":18,"Section":"Instruments","HS2 ID":1892,"HS2":"Musical instruments","Trade Value":36923},{"Section ID":20,"Section":"Miscellaneous","HS2 ID":2094,"HS2":"Furniture, bedding, lamps, & prefab buildings","Trade Value":4556649},{"Section ID":20,"Section":"Miscellaneous","HS2 ID":2095,"HS2":"Toys, games, & sports","Trade Value":16429064},{"Section ID":20,"Section":"Miscellaneous","HS2 ID":2096,"HS2":"Misc. manufactures","Trade Value":2058443},{"Section ID":21,"Section":"Arts and Antiques","HS2 ID":2197,"HS2":"Art & antiques","Trade Value":261483}]